Metadata-Version: 2.1
Name: totem
Version: 0.2.2
Summary: Software to verify that PRs and commits follow expected Quality Standards
Home-page: https://github.com/transifex/totem
Author: Transifex Devs
Author-email: info@transifex.com
License: UNKNOWN
Platform: UNKNOWN
Classifier: Programming Language :: Python :: 3.6
Classifier: License :: OSI Approved :: MIT License
Classifier: Operating System :: OS Independent
Requires-Dist: Click
Requires-Dist: PyGitHub (==1.40a4)
Requires-Dist: pyaml (==17.12.1)
Requires-Dist: GitPython (==2.1.11)
